{
  "students": [
    {
      "id": "1746427601746",
      "firstName": "da",
      "lastName": "da",
      "birthDate": "2025-05-22",
      "classId": "2"
    },
    {
      "id": "1746429920839",
      "firstName": "Ali",
      "lastName": "Jakbaarov",
      "birthDate": "2025-04-30",
      "classId": "2"
    },
    {
      "id": "1746431369076",
      "firstName": "da",
      "lastName": "da",
      "birthDate": "2025-05-16",
      "classId": null
    },
    {
      "id": "1746431715425",
      "firstName": "DA",
      "lastName": "DAS",
      "birthDate": "2025-05-17",
      "classId": "1746431700690"
    }
  ],
  "classes": [
    {
      "id": "1",
      "name": "Urushqoqlar",
      "studentCount": 1,
      "teacherId": null
    },
    {
      "id": "2",
      "name": "Esliklar",
      "studentCount": 1,
      "teacherId": "2"
    },
    {
      "id": "1746431700690",
      "name": "DAS",
      "teacherId": "2",
      "studentCount": 0
    }
  ],
  "teachers": [
    {
      "id": "2",
      "firstName": "Adham",
      "lastName": "Mirzayev",
      "birthDate": "11-11-1989"
    }
  ],
  "school": {
    "name": "144-sonli Umumta'lim maktabi",
    "location": "Muqiymiy ko'ch. 100 uy",
    "overallStudentCount": 1,
    "overallStaffCount": 1,
    "overallClassCount": 1,
    "about": "Yaxshi maktab!",
    "phoneNumber": "+9989565555551"
  }
}